easy_event_study/.DS_Store
easy_event_study/__init__.py
easy_event_study/base.py
easy_event_study/data_loader.py
easy_event_study/estimation_models.py
easy_event_study/event_study_model.py
easy_event_study/utils.py
easy_event_study-0.1.3.dist-info/WHEEL
easy_event_study-0.1.3.dist-info/entry_points.txt
easy_event_study-0.1.3.dist-info/METADATA
easy_event_study-0.1.3.dist-info/RECORD
