Metadata-Version: 2.3
Name: easy-event-study
Version: 0.1.3
Summary: A package to conduct financial event study with few lines of code.
Author: Vladislav Pyzhov
Author-email: Vladislav Pyzhov <vladpyzhov@gmail.com>
Requires-Dist: ipykernel>=6.30.1
Requires-Dist: nbformat>=5.10.4
Requires-Dist: numpy>=2.3.3
Requires-Dist: pandas>=2.3.3
Requires-Dist: plotly>=6.3.1
Requires-Dist: pytest>=8.4.2
Requires-Dist: python-dateutil>=2.9.0.post0
Requires-Dist: scikit-learn>=1.7.2
Requires-Dist: scipy>=1.16.2
Requires-Dist: setuptools==70.0.0
Requires-Dist: statsmodels>=0.14.5
Requires-Dist: tqdm>=4.67.1
Requires-Dist: typing-extensions>=4.15.0
Requires-Dist: yfinance>=0.2.66
Requires-Python: >=3.12
